{
  "name": "FINAL FANTASY RELAY RACE",
  "nameJa": "ファイナルファンタジー リレーレース",
  "url": "https://ffrelay.com",
  "tagline": "A speedrun relay race through the Final Fantasy series.",
  "taglineJa": "ファイナルファンタジーシリーズを駆け抜ける、スピードランリレーレース。",
  "youtube": "RPGLimitBreak",
  "twitch": "rpglimitbreak",
  "twitchJa": "japanese_restream",
  "eventNumber": "XI",
  "eventDates": "21st – 24th May 2026",
  "eventDatesJa": "2026年5月21日 – 24日",
  "startDate": "2026-05-21",
  "sheet": {
    "sheetId": "11Hljc51G9IP3Qf15F08hXtoaBE-LH0LT4HzwQ8AyMiQ",
    "tabs": {
      "info": "0",
      "splits": "182043132",
      "schedule": "1556535328"
    }
  }
}
